main.py
kuberdon-0.0.1.dist-info/LICENSE
kuberdon-0.0.1.dist-info/METADATA
kuberdon-0.0.1.dist-info/WHEEL
kuberdon-0.0.1.dist-info/top_level.txt
kuberdon-0.0.1.dist-info/RECORD
