Metadata-Version: 2.1
Name: kuberdon
Version: 0.0.1
Summary: kuberdon description
Author-email: Example Author <author@example.com>
Project-URL: Homepage, https://github.com/kuberdon
Project-URL: Bug Tracker, https://github.com/kuberdon/issues
Classifier: Programming Language :: Python :: 3
Classifier: License :: OSI Approved :: MIT License
Classifier: Operating System :: OS Independent
Requires-Python: >=3.7
License-File: LICENSE
